crude_dev/__init__.py
crude_dev/cli.py
crude_dev/spark.py
crude.dev-0.1.2.dist-info/entry_points.txt
crude.dev-0.1.2.dist-info/WHEEL
crude.dev-0.1.2.dist-info/METADATA
crude.dev-0.1.2.dist-info/RECORD
